Workbook
Name Accessories: Lists!$B$2:$B$1048576
Name Electronics: Lists!$A$2:$A$1048576
Name Office: Lists!$C$2:$C$1048576
Name ProductCategories: OFFSET(Product_List!$B$2,0,0,COUNTA(Product_List!$B:$B)-1,1)
Name Slicer_Category: #N/A
Name Slicer_Region: #N/A

Sheet PivotTables
A3: Row Labels | B3: Sum of Revenue | C3: Sum of Profit
A4: East | B4: 104142 | C4: -707979
A5: North | B5: 87013 | C5: -717319
A6: South | B6: 124308 | C6: -723765
A7: West | B7: 125799 | C7: -718096
A8: Grand Total | B8: 441262 | C8: -2867159

Sheet Sheet11
A3: Row Labels | B3: Sum of Net Profit
A4: Accessories | B4: -1887103
A5: Electronics | B5: -6156763
A6: Office | B6: -1524515
A7: Grand Total | B7: -9568381

Sheet Sales_All
A1: OrderID | B1: Date | C1: Region | D1: CustomerID | E1: Product | F1: Category | G1: UnitCost | H1: Discount | I1: Quantity | J1: UnitPrice | K1: Month | L1: Overheads | M1: Salaries | N1: Net Profit | O1: Delivery Days | P1: Return Rate | Q1: Revenue | R1: Discounted Revenue | S1: Profit | T1: Customer Type | U1: Product Details | V1: Purchase
A2: Q1-001 | B2: 45708.027 | C2: South | D2: 1018 | E2: Tablet | F2: =_xlfn.XLOOKUP(Sales_All[[#This Row],[Product]], Product_List!A:A, Product_List!B:B,) -> Electronics | G2: =_xlfn.XLOOKUP(Sales_All[[#This Row],[Product]], Product_List!A:A, Product_List!D:D) -> 492 | H2: =_xlfn.XLOOKUP(Sales_All[[#This Row],[Product]], Product_List!A:A, Product_List!E:E) -> 0.14 | I2: 1 | J2: 730 | K2: =EOMONTH(Sales_All[[#This Row],[Date]],0) -> 45716 | L2: =_xlfn.XLOOKUP(Sales_All[[#This Row],[Month]], Finance_Data!A:A, Finance_Data!B:B) -> 43320 | M2: =_xlfn.XLOOKUP(Sales_All[[#This Row],[Month]], Finance_Data!A:A, Finance_Data!C:C, 0) -> 70533 | N2: =(Sales_All[[#This Row],[Quantity]]*Sales_All[[#This Row],[UnitPrice]]) - (Sales_All[[#This Row],[Quantity]]*Sales_All[[#This Row],[UnitCost]]) - Sales_All[[#This Row],[Overheads]] -Sales_All[[#This Row],[Salaries]] -> -113615 | O2: =_xlfn.XLOOKUP(Sales_All[[#This Row],[OrderID]], Operations_Data!A:A, Operations_Data!B:B) -> 5 | P2: =_xlfn.XLOOKUP(Sales_All[[#This Row],[OrderID]], Operations_Data!A:A, Operations_Data!C:C) -> 0.01 | Q2: =Sales_All[[#This Row],[Quantity]]*Sales_All[[#This Row],[UnitPrice]] -> 730 | R2: =Sales_All[[#This Row],[Revenue]]*(1-Sales_All[[#This Row],[Discount]]) -> 627.8 | S2: =Sales_All[[#This Row],[Revenue]] -(Sales_All[[#This Row],[Quantity]]*Sales_All[[#This Row],[UnitCost]])-Sales_All[[#This Row],[Overheads]] -> -43082 | T2: {=_xlfn.IFS(Sales_All[[#This Row],[Revenue]]>50000,"VIP",Sales_All[[#This Row],[Revenue]]>=20000,"Regular",Sales_All[[#This Row],[Revenue]]<20000,"Low Value")} -> Low Value | U2: =INDEX(Product_List!B:B, MATCH(Sales_All[[#This Row],[Product]], Product_List!A:A, 0)) -> Electronics | V2: {=_xlfn.TEXTJOIN(", ", TRUE,IF(Sales_All[CustomerID] = Sales_All[[#This Row],[CustomerID]], Sales_All[Product], ""))} -> Tablet, Smartphone, Headphones, Headphones, Monitor, Laptop
A3: Q1-002 | B3: 45712.237 | C3: South | D3: 1004 | E3: Headphones | F3: =_xlfn.XLOOKUP(Sales_All[[#This Row],[Product]], Product_List!A:A, Product_List!B:B,) -> Accessories | G3: =_xlfn.XLOOKUP(Sales_All[[#This Row],[Product]], Product_List!A:A, Product_List!D:D) -> 323 | H3: =_xlfn.XLOOKUP(Sales_All[[#This Row],[Product]], Product_List!A:A, Product_List!E:E) -> 0.1 | I3: 3 | J3: 378 | K3: =EOMONTH(Sales_All[[#This Row],[Date]],0) -> 45716 | L3: =_xlfn.XLOOKUP(Sales_All[[#This Row],[Month]], Finance_Data!A:A, Finance_Data!B:B) -> 43320 | M3: =_xlfn.XLOOKUP(Sales_All[[#This Row],[Month]], Finance_Data!A:A, Finance_Data!C:C, 0) -> 70533 | N3: =(Sales_All[[#This Row],[Quantity]]*Sales_All[[#This Row],[UnitPrice]]) - (Sales_All[[#This Row],[Quantity]]*Sales_All[[#This Row],[UnitCost]]) - Sales_All[[#This Row],[Overheads]] -Sales_All[[#This Row],[Salaries]] -> -113688 | O3: =_xlfn.XLOOKUP(Sales_All[[#This Row],[OrderID]], Operations_Data!A:A, Operations_Data!B:B) -> 2 | P3: =_xlfn.XLOOKUP(Sales_All[[#This Row],[OrderID]], Operations_Data!A:A, Operations_Data!C:C) -> 0.03 | Q3: =Sales_All[[#This Row],[Quantity]]*Sales_All[[#This Row],[UnitPrice]] -> 1134 | R3: =Sales_All[[#This Row],[Revenue]]*(1-Sales_All[[#This Row],[Discount]]) -> 1020.6 | S3: =Sales_All[[#This Row],[Revenue]] -(Sales_All[[#This Row],[Quantity]]*Sales_All[[#This Row],[UnitCost]])-Sales_All[[#This Row],[Overheads]] -> -43155 | T3: {=_xlfn.IFS(Sales_All[[#This Row],[Revenue]]>50000,"VIP",Sales_All[[#This Row],[Revenue]]>=20000,"Regular",Sales_All[[#This Row],[Revenue]]<20000,"Low Value")} -> Low Value | U3: =INDEX(Product_List!B:B, MATCH(Sales_All[[#This Row],[Product]], Product_List!A:A, 0)) -> Accessories | V3: {=_xlfn.TEXTJOIN(", ", TRUE,IF(Sales_All[CustomerID] = Sales_All[[#This Row],[CustomerID]], Sales_All[Product], ""))} -> Headphones, Printer, Laptop
A4: Q1-003 | B4: 45736.268 | C4: West | D4: 1005 | E4: Monitor | F4: =_xlfn.XLOOKUP(Sales_All[[#This Row],[Product]], Product_List!A:A, Product_List!B:B,) -> Electronics | G4: =_xlfn.XLOOKUP(Sales_All[[#This Row],[Product]], Product_List!A:A, Product_List!D:D) -> 463 | H4: =_xlfn.XLOOKUP(Sales_All[[#This Row],[Product]], Product_List!A:A, Product_List!E:E) -> 0.23 | I4: 1 | J4: 585 | K4: =EOMONTH(Sales_All[[#This Row],[Date]],0) -> 45747 | L4: =_xlfn.XLOOKUP(Sales_All[[#This Row],[Month]], Finance_Data!A:A, Finance_Data!B:B) -> 34147 | M4: =_xlfn.XLOOKUP(Sales_All[[#This Row],[Month]], Finance_Data!A:A, Finance_Data!C:C, 0) -> 63890 | N4: =(Sales_All[[#This Row],[Quantity]]*Sales_All[[#This Row],[UnitPrice]]) - (Sales_All[[#This Row],[Quantity]]*Sales_All[[#This Row],[UnitCost]]) - Sales_All[[#This Row],[Overheads]] -Sales_All[[#This Row],[Salaries]] -> -97915 | O4: =_xlfn.XLOOKUP(Sales_All[[#This Row],[OrderID]], Operations_Data!A:A, Operations_Data!B:B) -> 6 | P4: =_xlfn.XLOOKUP(Sales_All[[#This Row],[OrderID]], Operations_Data!A:A, Operations_Data!C:C) -> 0.05 | Q4: =Sales_All[[#This Row],[Quantity]]*Sales_All[[#This Row],[UnitPrice]] -> 585 | R4: =Sales_All[[#This Row],[Revenue]]*(1-Sales_All[[#This Row],[Discount]]) -> 450.45 | S4: =Sales_All[[#This Row],[Revenue]] -(Sales_All[[#This Row],[Quantity]]*Sales_All[[#This Row],[UnitCost]])-Sales_All[[#This Row],[Overheads]] -> -34025 | T4: {=_xlfn.IFS(Sales_All[[#This Row],[Revenue]]>50000,"VIP",Sales_All[[#This Row],[Revenue]]>=20000,"Regular",Sales_All[[#This Row],[Revenue]]<20000,"Low Value")} -> Low Value | U4: =INDEX(Product_List!B:B, MATCH(Sales_All[[#This Row],[Product]], Product_List!A:A, 0)) -> Electronics | V4: {=_xlfn.TEXTJOIN(", ", TRUE,IF(Sales_All[CustomerID] = Sales_All[[#This Row],[CustomerID]], Sales_All[Product], ""))} -> Monitor, Printer, Printer, Printer, Tablet
A5: Q1-004 | B5: 45703.571 | C5: East | D5: 1018 | E5: Smartphone | F5: =_xlfn.XLOOKUP(Sales_All[[#This Row],[Product]], Product_List!A:A, Product_List!B:B,) -> Electronics | G5: =_xlfn.XLOOKUP(Sales_All[[#This Row],[Product]], Product_List!A:A, Product_List!D:D) -> 97 | H5: =_xlfn.XLOOKUP(Sales_All[[#This Row],[Product]], Product_List!A:A, Product_List!E:E) -> 0.08 | I5: 8 | J5: 726 | K5: =EOMONTH(Sales_All[[#This Row],[Date]],0) -> 45716 | L5: =_xlfn.XLOOKUP(Sales_All[[#This Row],[Month]], Finance_Data!A:A, Finance_Data!B:B) -> 43320 | M5: =_xlfn.XLOOKUP(Sales_All[[#This Row],[Month]], Finance_Data!A:A, Finance_Data!C:C, 0) -> 70533 | N5: =(Sales_All[[#This Row],[Quantity]]*Sales_All[[#This Row],[UnitPrice]]) - (Sales_All[[#This Row],[Quantity]]*Sales_All[[#This Row],[UnitCost]]) - Sales_All[[#This Row],[Overheads]] -Sales_All[[#This Row],[Salaries]] -> -108821 | O5: =_xlfn.XLOOKUP(Sales_All[[#This Row],[OrderID]], Operations_Data!A:A, Operations_Data!B:B) -> 4 | P5: =_xlfn.XLOOKUP(Sales_All[[#This Row],[OrderID]], Operations_Data!A:A, Operations_Data!C:C) -> 0.07 | Q5: =Sales_All[[#This Row],[Quantity]]*Sales_All[[#This Row],[UnitPrice]] -> 5808 | R5: =Sales_All[[#This Row],[Revenue]]*(1-Sales_All[[#This Row],[Discount]]) -> 5343.36 | S5: =Sales_All[[#This Row],[Revenue]] -(Sales_All[[#This Row],[Quantity]]*Sales_All[[#This Row],[UnitCost]])-Sales_All[[#This Row],[Overheads]] -> -38288 | T5: {=_xlfn.IFS(Sales_All[[#This Row],[Revenue]]>50000,"VIP",Sales_All[[#This Row],[Revenue]]>=20000,"Regular",Sales_All[[#This Row],[Revenue]]<20000,"Low Value")} -> Low Value | U5: =INDEX(Product_List!B:B, MATCH(Sales_All[[#This Row],[Product]], Product_List!A:A, 0)) -> Electronics | V5: {=_xlfn.TEXTJOIN(", ", TRUE,IF(Sales_All[CustomerID] = Sales_All[[#This Row],[CustomerID]], Sales_All[Product], ""))} -> Tablet, Smartphone, Headphones, Headphones, Monitor, Laptop
A6: Q1-005 | B6: 45663.686 | C6: North | D6: 1012 | E6: Laptop | F6: =_xlfn.XLOOKUP(Sales_All[[#This Row],[Product]], Product_List!A:A, Product_List!B:B,) -> Electronics | G6: =_xlfn.XLOOKUP(Sales_All[[#This Row],[Product]], Product_List!A:A, Product_List!D:D) -> 469 | H6: =_xlfn.XLOOKUP(Sales_All[[#This Row],[Product]], Product_List!A:A, Product_List!E:E) -> 0.22 | I6: 2 | J6: 709 | K6: =EOMONTH(Sales_All[[#This Row],[Date]],0) -> 45688 | L6: =_xlfn.XLOOKUP(Sales_All[[#This Row],[Month]], Finance_Data!A:A, Finance_Data!B:B) -> 25640 | M6: =_xlfn.XLOOKUP(Sales_All[[#This Row],[Month]], Finance_Data!A:A, Finance_Data!C:C, 0) -> 60082 | N6: =(Sales_All[[#This Row],[Quantity]]*Sales_All[[#This Row],[UnitPrice]]) - (Sales_All[[#This Row],[Quantity]]*Sales_All[[#This Row],[UnitCost]]) - Sales_All[[#This Row],[Overheads]] -Sales_All[[#This Row],[Salaries]] -> -85242 | O6: =_xlfn.XLOOKUP(Sales_All[[#This Row],[OrderID]], Operations_Data!A:A, Operations_Data!B:B) -> 5 | P6: =_xlfn.XLOOKUP(Sales_All[[#This Row],[OrderID]], Operations_Data!A:A, Operations_Data!C:C) -> 0.03 | Q6: =Sales_All[[#This Row],[Quantity]]*Sales_All[[#This Row],[UnitPrice]] -> 1418 | R6: =Sales_All[[#This Row],[Revenue]]*(1-Sales_All[[#This Row],[Discount]]) -> 1106.04 | S6: =Sales_All[[#This Row],[Revenue]] -(Sales_All[[#This Row],[Quantity]]*Sales_All[[#This Row],[UnitCost]])-Sales_All[[#This Row],[Overheads]] -> -25160 | T6: {=_xlfn.IFS(Sales_All[[#This Row],[Revenue]]>50000,"VIP",Sales_All[[#This Row],[Revenue]]>=20000,"Regular",Sales_All[[#This Row],[Revenue]]<20000,"Low Value")} -> Low Value | U6: =INDEX(Product_List!B:B, MATCH(Sales_All[[#This Row],[Product]], Product_List!A:A, 0)) -> Electronics | V6: {=_xlfn.TEXTJOIN(", ", TRUE,IF(Sales_All[CustomerID] = Sales_All[[#This Row],[CustomerID]], Sales_All[Product], ""))} -> Laptop, Headphones, Printer, Monitor
A7: Q1-006 | B7: 45716.227 | C7: East | D7: 1013 | E7: Laptop | F7: =_xlfn.XLOOKUP(Sales_All[[#This Row],[Product]], Product_List!A:A, Product_List!B:B,) -> Electronics | G7: =_xlfn.XLOOKUP(Sales_All[[#This Row],[Product]], Product_List!A:A, Product_List!D:D) -> 469 | H7: =_xlfn.XLOOKUP(Sales_All[[#This Row],[Product]], Product_List!A:A, Product_List!E:E) -> 0.22 | I7: 8 | J7: 1817 | K7: =EOMONTH(Sales_All[[#This Row],[Date]],0) -> 45716 | L7: =_xlfn.XLOOKUP(Sales_All[[#This Row],[Month]], Finance_Data!A:A, Finance_Data!B:B) -> 43320 | M7: =_xlfn.XLOOKUP(Sales_All[[#This Row],[Month]], Finance_Data!A:A, Finance_Data!C:C, 0) -> 70533 | N7: =(Sales_All[[#This Row],[Quantity]]*Sales_All[[#This Row],[UnitPrice]]) - (Sales_All[[#This Row],[Quantity]]*Sales_All[[#This Row],[UnitCost]]) - Sales_All[[#This Row],[Overheads]] -Sales_All[[#This Row],[Salaries]] -> -103069 | O7: =_xlfn.XLOOKUP(Sales_All[[#This Row],[OrderID]], Operations_Data!A:A, Operations_Data!B:B) -> 5 | P7: =_xlfn.XLOOKUP(Sales_All[[#This Row],[OrderID]], Operations_Data!A:A, Operations_Data!C:C) -> 0.06 | Q7: =Sales_All[[#This Row],[Quantity]]*Sales_All[[#This Row],[UnitPrice]] -> 14536 | R7: =Sales_All[[#This Row],[Revenue]]*(1-Sales_All[[#This Row],[Discount]]) -> 11338.08 | S7: =Sales_All[[#This Row],[Revenue]] -(Sales_All[[#This Row],[Quantity]]*Sales_All[[#This Row],[UnitCost]])-Sales_All[[#This Row],[Overheads]] -> -32536 | T7: {=_xlfn.IFS(Sales_All[[#This Row],[Revenue]]>50000,"VIP",Sales_All[[#This Row],[Revenue]]>=20000,"Regular",Sales_All[[#This Row],[Revenue]]<20000,"Low Value")} -> Low Value | U7: =INDEX(Product_List!B:B, MATCH(Sales_All[[#This Row],[Product]], Product_List!A:A, 0)) -> Electronics | V7: {=_xlfn.TEXTJOIN(", ", TRUE,IF(Sales_All[CustomerID] = Sales_All[[#This Row],[CustomerID]], Sales_All[Product], ""))} -> Laptop, Printer
A8: Q1-007 | B8: 45735.116 | C8: South | D8: 1017 | E8: Tablet | F8: =_xlfn.XLOOKUP(Sales_All[[#This Row],[Product]], Product_List!A:A, Product_List!B:B,) -> Electronics | G8: =_xlfn.XLOOKUP(Sales_All[[#This Row],[Product]], Product_List!A:A, Product_List!D:D) -> 492 | H8: =_xlfn.XLOOKUP(Sales_All[[#This Row],[Product]], Product_List!A:A, Product_List!E:E) -> 0.14 | I8: 9 | J8: 1976 | K8: =EOMONTH(Sales_All[[#This Row],[Date]],0) -> 45747 | L8: =_xlfn.XLOOKUP(Sales_All[[#This Row],[Month]], Finance_Data!A:A, Finance_Data!B:B) -> 34147 | M8: =_xlfn.XLOOKUP(Sales_All[[#This Row],[Month]], Finance_Data!A:A, Finance_Data!C:C, 0) -> 63890 | N8: =(Sales_All[[#This Row],[Quantity]]*Sales_All[[#This Row],[UnitPrice]]) - (Sales_All[[#This Row],[Quantity]]*Sales_All[[#This Row],[UnitCost]]) - Sales_All[[#This Row],[Overheads]] -Sales_All[[#This Row],[Salaries]] -> -84681 | O8: =_xlfn.XLOOKUP(Sales_All[[#This Row],[OrderID]], Operations_Data!A:A, Operations_Data!B:B) -> 4 | P8: =_xlfn.XLOOKUP(Sales_All[[#This Row],[OrderID]], Operations_Data!A:A, Operations_Data!C:C) -> 0.02 | Q8: =Sales_All[[#This Row],[Quantity]]*Sales_All[[#This Row],[UnitPrice]] -> 17784 | R8: =Sales_All[[#This Row],[Revenue]]*(1-Sales_All[[#This Row],[Discount]]) -> 15294.24 | S8: =Sales_All[[#This Row],[Revenue]] -(Sales_All[[#This Row],[Quantity]]*Sales_All[[#This Row],[UnitCost]])-Sales_All[[#This Row],[Overheads]] -> -20791 | T8: {=_xlfn.IFS(Sales_All[[#This Row],[Revenue]]>50000,"VIP",Sales_All[[#This Row],[Revenue]]>=20000,"Regular",Sales_All[[#This Row],[Revenue]]<20000,"Low Value")} -> Low Value | U8: =INDEX(Product_List!B:B, MATCH(Sales_All[[#This Row],[Product]], Product_List!A:A, 0)) -> Electronics | V8: {=_xlfn.TEXTJOIN(", ", TRUE,IF(Sales_All[CustomerID] = Sales_All[[#This Row],[CustomerID]], Sales_All[Product], ""))} -> Tablet, Laptop, Printer, Laptop, Smartphone
A9: Q1-008 | B9: 45707.394 | C9: South | D9: 1014 | E9: Tablet | F9: =_xlfn.XLOOKUP(Sales_All[[#This Row],[Product]], Product_List!A:A, Product_List!B:B,) -> Electronics | G9: =_xlfn.XLOOKUP(Sales_All[[#This Row],[Product]], Product_List!A:A, Product_List!D:D) -> 492 | H9: =_xlfn.XLOOKUP(Sales_All[[#This Row],[Product]], Product_List!A:A, Product_List!E:E) -> 0.14 | I9: 5 | J9: 1134 | K9: =EOMONTH(Sales_All[[#This Row],[Date]],0) -> 45716 | L9: =_xlfn.XLOOKUP(Sales_All[[#This Row],[Month]], Finance_Data!A:A, Finance_Data!B:B) -> 43320 | M9: =_xlfn.XLOOKUP(Sales_All[[#This Row],[Month]], Finance_Data!A:A, Finance_Data!C:C, 0) -> 70533 | N9: =(Sales_All[[#This Row],[Quantity]]*Sales_All[[#This Row],[UnitPrice]]) - (Sales_All[[#This Row],[Quantity]]*Sales_All[[#This Row],[UnitCost]]) - Sales_All[[#This Row],[Overheads]] -Sales_All[[#This Row],[Salaries]] -> -110643 | O9: =_xlfn.XLOOKUP(Sales_All[[#This Row],[OrderID]], Operations_Data!A:A, Operations_Data!B:B) -> 8 | P9: =_xlfn.XLOOKUP(Sales_All[[#This Row],[OrderID]], Operations_Data!A:A, Operations_Data!C:C) -> 0.07 | Q9: =Sales_All[[#This Row],[Quantity]]*Sales_All[[#This Row],[UnitPrice]] -> 5670 | R9: =Sales_All[[#This Row],[Revenue]]*(1-Sales_All[[#This Row],[Discount]]) -> 4876.2 | S9: =Sales_All[[#This Row],[Revenue]] -(Sales_All[[#This Row],[Quantity]]*Sales_All[[#This Row],[UnitCost]])-Sales_All[[#This Row],[Overheads]] -> -40110 | T9: {=_xlfn.IFS(Sales_All[[#This Row],[Revenue]]>50000,"VIP",Sales_All[[#This Row],[Revenue]]>=20000,"Regular",Sales_All[[#This Row],[Revenue]]<20000,"Low Value")} -> Low Value | U9: =INDEX(Product_List!B:B, MATCH(Sales_All[[#This Row],[Product]], Product_List!A:A, 0)) -> Electronics | V9: {=_xlfn.TEXTJOIN(", ", TRUE,IF(Sales_All[CustomerID] = Sales_All[[#This Row],[CustomerID]], Sales_All[Product], ""))} -> Tablet, Monitor, Headphones
A10: Q1-009 | B10: 45671.497 | C10: South | D10: 1020 | E10: Printer | F10: =_xlfn.XLOOKUP(Sales_All[[#This Row],[Product]], Product_List!A:A, Product_List!B:B,) -> Office | G10: =_xlfn.XLOOKUP(Sales_All[[#This Row],[Product]], Product_List!A:A, Product_List!D:D) -> 136 | H10: =_xlfn.XLOOKUP(Sales_All[[#This Row],[Product]], Product_List!A:A, Product_List!E:E) -> 0.1 | I10: 1 | J10: 1220 | K10: =EOMONTH(Sales_All[[#This Row],[Date]],0) -> 45688 | L10: =_xlfn.XLOOKUP(Sales_All[[#This Row],[Month]], Finance_Data!A:A, Finance_Data!B:B) -> 25640 | M10: =_xlfn.XLOOKUP(Sales_All[[#This Row],[Month]], Finance_Data!A:A, Finance_Data!C:C, 0) -> 60082 | N10: =(Sales_All[[#This Row],[Quantity]]*Sales_All[[#This Row],[UnitPrice]]) - (Sales_All[[#This Row],[Quantity]]*Sales_All[[#This Row],[UnitCost]]) - Sales_All[[#This Row],[Overheads]] -Sales_All[[#This Row],[Salaries]] -> -84638 | O10: =_xlfn.XLOOKUP(Sales_All[[#This Row],[OrderID]], Operations_Data!A:A, Operations_Data!B:B) -> 2 | P10: =_xlfn.XLOOKUP(Sales_All[[#This Row],[OrderID]], Operations_Data!A:A, Operations_Data!C:C) -> 0.08 | Q10: =Sales_All[[#This Row],[Quantity]]*Sales_All[[#This Row],[UnitPrice]] -> 1220 | R10: =Sales_All[[#This Row],[Revenue]]*(1-Sales_All[[#This Row],[Discount]]) -> 1098 | S10: =Sales_All[[#This Row],[Revenue]] -(Sales_All[[#This Row],[Quantity]]*Sales_All[[#This Row],[UnitCost]])-Sales_All[[#This Row],[Overheads]] -> -24556 | T10: {=_xlfn.IFS(Sales_All[[#This Row],[Revenue]]>50000,"VIP",Sales_All[[#This Row],[Revenue]]>=20000,"Regular",Sales_All[[#This Row],[Revenue]]<20000,"Low Value")} -> Low Value | U10: =INDEX(Product_List!B:B, MATCH(Sales_All[[#This Row],[Product]], Product_List!A:A, 0)) -> Office | V10: {=_xlfn.TEXTJOIN(", ", TRUE,IF(Sales_All[CustomerID] = Sales_All[[#This Row],[CustomerID]], Sales_All[Product], ""))} -> Printer, Headphones, Laptop, Printer
A11: Q1-010 | B11: 45743.202 | C11: West | D11: 1010 | E11: Headphones | F11: =_xlfn.XLOOKUP(Sales_All[[#This Row],[Product]], Product_List!A:A, Product_List!B:B,) -> Accessories | G11: =_xlfn.XLOOKUP(Sales_All[[#This Row],[Product]], Product_List!A:A, Product_List!D:D) -> 323 | H11: =_xlfn.XLOOKUP(Sales_All[[#This Row],[Product]], Product_List!A:A, Product_List!E:E) -> 0.1 | I11: 2 | J11: 283 | K11: =EOMONTH(Sales_All[[#This Row],[Date]],0) -> 45747 | L11: =_xlfn.XLOOKUP(Sales_All[[#This Row],[Month]], Finance_Data!A:A, Finance_Data!B:B) -> 34147 | M11: =_xlfn.XLOOKUP(Sales_All[[#This Row],[Month]], Finance_Data!A:A, Finance_Data!C:C, 0) -> 63890 | N11: =(Sales_All[[#This Row],[Quantity]]*Sales_All[[#This Row],[UnitPrice]]) - (Sales_All[[#This Row],[Quantity]]*Sales_All[[#This Row],[UnitCost]]) - Sales_All[[#This Row],[Overheads]] -Sales_All[[#This Row],[Salaries]] -> -98117 | O11: =_xlfn.XLOOKUP(Sales_All[[#This Row],[OrderID]], Operations_Data!A:A, Operations_Data!B:B) -> 2 | P11: =_xlfn.XLOOKUP(Sales_All[[#This Row],[OrderID]], Operations_Data!A:A, Operations_Data!C:C) -> 0.08 | Q11: =Sales_All[[#This Row],[Quantity]]*Sales_All[[#This Row],[UnitPrice]] -> 566 | R11: =Sales_All[[#This Row],[Revenue]]*(1-Sales_All[[#This Row],[Discount]]) -> 509.4 | S11: =Sales_All[[#This Row],[Revenue]] -(Sales_All[[#This Row],[Quantity]]*Sales_All[[#This Row],[UnitCost]])-Sales_All[[#This Row],[Overheads]] -> -34227 | T11: {=_xlfn.IFS(Sales_All[[#This Row],[Revenue]]>50000,"VIP",Sales_All[[#This Row],[Revenue]]>=20000,"Regular",Sales_All[[#This Row],[Revenue]]<20000,"Low Value")} -> Low Value | U11: =INDEX(Product_List!B:B, MATCH(Sales_All[[#This Row],[Product]], Product_List!A:A, 0)) -> Accessories | V11: {=_xlfn.TEXTJOIN(", ", TRUE,IF(Sales_All[CustomerID] = Sales_All[[#This Row],[CustomerID]], Sales_All[Product], ""))} -> Headphones, Headphones, Smartphone, Monitor, Printer, Printer, Smartphone
A12: Q1-011 | B12: 45684.929 | C12: West | D12: 1019 | E12: Laptop | F12: =_xlfn.XLOOKUP(Sales_All[[#This Row],[Product]], Product_List!A:A, Product_List!B:B,) -> Electronics | G12: =_xlfn.XLOOKUP(Sales_All[[#This Row],[Product]], Product_List!A:A, Product_List!D:D) -> 469 | H12: =_xlfn.XLOOKUP(Sales_All[[#This Row],[Product]], Product_List!A:A, Product_List!E:E) -> 0.22 | I12: 9 | J12: 417 | K12: =EOMONTH(Sales_All[[#This Row],[Date]],0) -> 45688 | L12: =_xlfn.XLOOKUP(Sales_All[[#This Row],[Month]], Finance_Data!A:A, Finance_Data!B:B) -> 25640 | M12: =_xlfn.XLOOKUP(Sales_All[[#This Row],[Month]], Finance_Data!A:A, Finance_Data!C:C, 0) -> 60082 | N12: =(Sales_All[[#This Row],[Quantity]]*Sales_All[[#This Row],[UnitPrice]]) - (Sales_All[[#This Row],[Quantity]]*Sales_All[[#This Row],[UnitCost]]) - Sales_All[[#This Row],[Overheads]] -Sales_All[[#This Row],[Salaries]] -> -86190 | O12: =_xlfn.XLOOKUP(Sales_All[[#This Row],[OrderID]], Operations_Data!A:A, Operations_Data!B:B) -> 8 | P12: =_xlfn.XLOOKUP(Sales_All[[#This Row],[OrderID]], Operations_Data!A:A, Operations_Data!C:C) -> 0.06 | Q12: =Sales_All[[#This Row],[Quantity]]*Sales_All[[#This Row],[UnitPrice]] -> 3753 | R12: =Sales_All[[#This Row],[Revenue]]*(1-Sales_All[[#This Row],[Discount]]) -> 2927.34 | S12: =Sales_All[[#This Row],[Revenue]] -(Sales_All[[#This Row],[Quantity]]*Sales_All[[#This Row],[UnitCost]])-Sales_All[[#This Row],[Overheads]] -> -26108 | T12: {=_xlfn.IFS(Sales_All[[#This Row],[Revenue]]>50000,"VIP",Sales_All[[#This Row],[Revenue]]>=20000,"Regular",Sales_All[[#This Row],[Revenue]]<20000,"Low Value")} -> Low Value | U12: =INDEX(Product_List!B:B, MATCH(Sales_All[[#This Row],[Product]], Product_List!A:A, 0)) -> Electronics | V12: {=_xlfn.TEXTJOIN(", ", TRUE,IF(Sales_All[CustomerID] = Sales_All[[#This Row],[CustomerID]], Sales_All[Product], ""))} -> Laptop, Laptop, Headphones, Laptop, Tablet, Tablet, Monitor
A13: Q1-012 | B13: 45662.79 | C13: South | D13: 1016 | E13: Laptop | F13: =_xlfn.XLOOKUP(Sales_All[[#This Row],[Product]], Product_List!A:A, Product_List!B:B,) -> Electronics | G13: =_xlfn.XLOOKUP(Sales_All[[#This Row],[Product]], Product_List!A:A, Product_List!D:D) -> 469 | H13: =_xlfn.XLOOKUP(Sales_All[[#This Row],[Product]], Product_List!A:A, Product_List!E:E) -> 0.22 | I13: 3 | J13: 1692 | K13: =EOMONTH(Sales_All[[#This Row],[Date]],0) -> 45688 | L13: =_xlfn.XLOOKUP(Sales_All[[#This Row],[Month]], Finance_Data!A:A, Finance_Data!B:B) -> 25640 | M13: =_xlfn.XLOOKUP(Sales_All[[#This Row],[Month]], Finance_Data!A:A, Finance_Data!C:C, 0) -> 60082 | N13: =(Sales_All[[#This Row],[Quantity]]*Sales_All[[#This Row],[UnitPrice]]) - (Sales_All[[#This Row],[Quantity]]*Sales_All[[#This Row],[UnitCost]]) - Sales_All[[#This Row],[Overheads]] -Sales_All[[#This Row],[Salaries]] -> -82053 | O13: =_xlfn.XLOOKUP(Sales_All[[#This Row],[OrderID]], Operations_Data!A:A, Operations_Data!B:B) -> 8 | P13: =_xlfn.XLOOKUP(Sales_All[[#This Row],[OrderID]], Operations_Data!A:A, Operations_Data!C:C) -> 0.03 | Q13: =Sales_All[[#This Row],[Quantity]]*Sales_All[[#This Row],[UnitPrice]] -> 5076 | R13: =Sales_All[[#This Row],[Revenue]]*(1-Sales_All[[#This Row],[Discount]]) -> 3959.28 | S13: =Sales_All[[#This Row],[Revenue]] -(Sales_All[[#This Row],[Quantity]]*Sales_All[[#This Row],[UnitCost]])-Sales_All[[#This Row],[Overheads]] -> -21971 | T13: {=_xlfn.IFS(Sales_All[[#This Row],[Revenue]]>50000,"VIP",Sales_All[[#This Row],[Revenue]]>=20000,"Regular",Sales_All[[#This Row],[Revenue]]<20000,"Low Value")} -> Low Value | U13: =INDEX(Product_List!B:B, MATCH(Sales_All[[#This Row],[Product]], Product_List!A:A, 0)) -> Electronics | V13: {=_xlfn.TEXTJOIN(", ", TRUE,IF(Sales_All[CustomerID] = Sales_All[[#This Row],[CustomerID]], Sales_All[Product], ""))} -> Laptop, Monitor, Monitor, Tablet
... A91: Q3-030 | B91: 45898.259 | C91: West | D91: 1003 | E91: Monitor | F91: =_xlfn.XLOOKUP(Sales_All[[#This Row],[Product]], Product_List!A:A, Product_List!B:B,) -> Electronics | G91: =_xlfn.XLOOKUP(Sales_All[[#This Row],[Product]], Product_List!A:A, Product_List!D:D) -> 463 | H91: =_xlfn.XLOOKUP(Sales_All[[#This Row],[Product]], Product_List!A:A, Product_List!E:E) -> 0.23 | I91: 3 | J91: 651 | K91: =EOMONTH(Sales_All[[#This Row],[Date]],0) -> 45900 | L91: =_xlfn.XLOOKUP(Sales_All[[#This Row],[Month]], Finance_Data!A:A, Finance_Data!B:B) -> 36734 | M91: =_xlfn.XLOOKUP(Sales_All[[#This Row],[Month]], Finance_Data!A:A, Finance_Data!C:C, 0) -> 93760 | N91: =(Sales_All[[#This Row],[Quantity]]*Sales_All[[#This Row],[UnitPrice]]) - (Sales_All[[#This Row],[Quantity]]*Sales_All[[#This Row],[UnitCost]]) - Sales_All[[#This Row],[Overheads]] -Sales_All[[#This Row],[Salaries]] -> -129930 | O91: =_xlfn.XLOOKUP(Sales_All[[#This Row],[OrderID]], Operations_Data!A:A, Operations_Data!B:B) -> 5 | P91: =_xlfn.XLOOKUP(Sales_All[[#This Row],[OrderID]], Operations_Data!A:A, Operations_Data!C:C) -> 0.09 | Q91: =Sales_All[[#This Row],[Quantity]]*Sales_All[[#This Row],[UnitPrice]] -> 1953 | R91: =Sales_All[[#This Row],[Revenue]]*(1-Sales_All[[#This Row],[Discount]]) -> 1503.81 | S91: =Sales_All[[#This Row],[Revenue]] -(Sales_All[[#This Row],[Quantity]]*Sales_All[[#This Row],[UnitCost]])-Sales_All[[#This Row],[Overheads]] -> -36170 | T91: {=_xlfn.IFS(Sales_All[[#This Row],[Revenue]]>50000,"VIP",Sales_All[[#This Row],[Revenue]]>=20000,"Regular",Sales_All[[#This Row],[Revenue]]<20000,"Low Value")} -> Low Value | U91: =INDEX(Product_List!B:B, MATCH(Sales_All[[#This Row],[Product]], Product_List!A:A, 0)) -> Electronics | V91: {=_xlfn.TEXTJOIN(", ", TRUE,IF(Sales_All[CustomerID] = Sales_All[[#This Row],[CustomerID]], Sales_All[Product], ""))} -> Printer, Monitor, Headphones, Monitor

Sheet VIP_Report

Sheet Lists
A1: Electronics | B1: Accessories | C1: Office
A2: Laptop | B2: Headphones | C2: Printer
A3: Tablet | B3: Cordless Mouse
A4: Smartphone
A5: Monitor

Sheet Summary
A1: Region | B1: Orders | C1: Average Delivery Days
A2: {=_xlfn.UNIQUE(Sales_All[Region])} -> South | B2: =COUNTIF(Sales_All[Region], A2) -> 23 | C2: =AVERAGEIF(Sales_All[Region],A2,Sales_All[Delivery Days]) -> 5.4347826
A3: West | B3: =COUNTIF(Sales_All[Region], A3) -> 24 | C3: =AVERAGEIF(Sales_All[Region],A3,Sales_All[Delivery Days]) -> 5.0833333
A4: East | B4: =COUNTIF(Sales_All[Region], A4) -> 21 | C4: =AVERAGEIF(Sales_All[Region],A4,Sales_All[Delivery Days]) -> 4.3809524
A5: North | B5: =COUNTIF(Sales_All[Region], A5) -> 22 | C5: =AVERAGEIF(Sales_All[Region],A5,Sales_All[Delivery Days]) -> 4.5909091

Sheet Customer_List
A1: CustomerID | B1: FirstName | C1: LastName | D1: Email | E1: Region | F1: ProperName | G1: ProperSurname | H1: Extraction
A2: 1001 | B2: Naledi | C2: Pillay | D2: naledi.pillay@example.com | E2: East | F2: =PROPER(Customers[[#This Row],[FirstName]]) -> Naledi | G2: =PROPER(Customers[[#This Row],[LastName]]) -> Pillay | H2: example.com
A3: 1002 | B3: Michael | C3: van Wyk | D3: michael.van wyk@example.com | E3: East | F3: =PROPER(Customers[[#This Row],[FirstName]]) -> Michael | G3: =PROPER(Customers[[#This Row],[LastName]]) -> Van Wyk | H3: example.com
A4: 1003 | B4: Naledi | C4: Botha | D4: naledi.botha@example.com | E4: East | F4: =PROPER(Customers[[#This Row],[FirstName]]) -> Naledi | G4: =PROPER(Customers[[#This Row],[LastName]]) -> Botha | H4: example.com
A5: 1004 | B5: Naledi | C5: Botha | D5: naledi.botha@example.com | E5: North | F5: =PROPER(Customers[[#This Row],[FirstName]]) -> Naledi | G5: =PROPER(Customers[[#This Row],[LastName]]) -> Botha | H5: example.com
A6: 1005 | B6: Michael | C6: Johnson | D6: michael.johnson@example.com | E6: North | F6: =PROPER(Customers[[#This Row],[FirstName]]) -> Michael | G6: =PROPER(Customers[[#This Row],[LastName]]) -> Johnson | H6: example.com
A7: 1006 | B7: Emily | C7: Johnson | D7: emily.johnson@example.com | E7: South | F7: =PROPER(Customers[[#This Row],[FirstName]]) -> Emily | G7: =PROPER(Customers[[#This Row],[LastName]]) -> Johnson | H7: example.com
A8: 1007 | B8: Michael | C8: Nguyen | D8: michael.nguyen@example.com | E8: West | F8: =PROPER(Customers[[#This Row],[FirstName]]) -> Michael | G8: =PROPER(Customers[[#This Row],[LastName]]) -> Nguyen | H8: example.com
A9: 1008 | B9: Sipho | C9: Johnson | D9: sipho.johnson@example.com | E9: East | F9: =PROPER(Customers[[#This Row],[FirstName]]) -> Sipho | G9: =PROPER(Customers[[#This Row],[LastName]]) -> Johnson | H9: example.com
A10: 1009 | B10: Sarah | C10: Nguyen | D10: sarah.nguyen@example.com | E10: North | F10: =PROPER(Customers[[#This Row],[FirstName]]) -> Sarah | G10: =PROPER(Customers[[#This Row],[LastName]]) -> Nguyen | H10: example.com
A11: 1010 | B11: John | C11: Brown | D11: john.brown@example.com | E11: East | F11: =PROPER(Customers[[#This Row],[FirstName]]) -> John | G11: =PROPER(Customers[[#This Row],[LastName]]) -> Brown | H11: example.com
A12: 1011 | B12: John | C12: Smith | D12: john.smith@example.com | E12: South | F12: =PROPER(Customers[[#This Row],[FirstName]]) -> John | G12: =PROPER(Customers[[#This Row],[LastName]]) -> Smith | H12: example.com
A13: 1012 | B13: Naledi | C13: van Wyk | D13: naledi.van wyk@example.com | E13: East | F13: =PROPER(Customers[[#This Row],[FirstName]]) -> Naledi | G13: =PROPER(Customers[[#This Row],[LastName]]) -> Van Wyk | H13: example.com
... A29: 1018 | B29: Michael | C29: Mlambo | D29: michael.mlambo@example.com | E29: South | F29: =PROPER(Customers[[#This Row],[FirstName]]) -> Michael | G29: =PROPER(Customers[[#This Row],[LastName]]) -> Mlambo | H29: example.com

Sheet Product_List
A1: Product | B1: Category | C1: UnitPrice | D1: UnitCost | E1: Discount
A2: Laptop | B2: Electronics | C2: 1299 | D2: 469 | E2: 0.22
A3: Tablet | B3: Electronics | C3: 1613 | D3: 492 | E3: 0.14
A4: Smartphone | B4: Electronics | C4: 1402 | D4: 97 | E4: 0.08
A5: Headphones | B5: Accessories | C5: 106 | D5: 323 | E5: 0.1
A6: Monitor | B6: Electronics | C6: 396 | D6: 463 | E6: 0.23
A7: Printer | B7: Office | C7: 1635 | D7: 136 | E7: 0.1

Sheet Finance_Data
A1: Month | B1: Overheads | C1: Salaries | D1: OtherExpenses | E1: Net Profit
A2: 45688 | B2: 25640 | C2: 60082 | D2: 21492 | E2: 85722
A3: 45716 | B3: 43320 | C3: 70533 | D3: 27724 | E3: 113853
A4: 45747 | B4: 34147 | C4: 63890 | D4: 17738 | E4: 98037
A5: 45777 | B5: 44423 | C5: 90674 | D5: 21152 | E5: 135097
A6: 45808 | B6: 32119 | C6: 55646 | D6: 19723 | E6: 87765
A7: 45838 | B7: 20079 | C7: 99954 | D7: 15769 | E7: 120033
A8: 45869 | B8: 36304 | C8: 63297 | D8: 25453 | E8: 99601
A9: 45900 | B9: 36734 | C9: 93760 | D9: 16230 | E9: 130494
A10: 45930 | B10: 34260 | C10: 70760 | D10: 28818 | E10: 105020

Sheet Operations_Data
A1: OrderID | B1: DeliveryDays | C1: ReturnRate | D1: Operational Effeciency
A2: Q1-001 | B2: 5 | C2: 0.01
A3: Q1-002 | B3: 2 | C3: 0.03
A4: Q1-003 | B4: 6 | C4: 0.05
A5: Q1-004 | B5: 4 | C5: 0.07
A6: Q1-005 | B6: 5 | C6: 0.03
A7: Q1-006 | B7: 5 | C7: 0.06
A8: Q1-007 | B8: 4 | C8: 0.02
A9: Q1-008 | B9: 8 | C9: 0.07
A10: Q1-009 | B10: 2 | C10: 0.08
A11: Q1-010 | B11: 2 | C11: 0.08
A12: Q1-011 | B12: 8 | C12: 0.06
A13: Q1-012 | B13: 8 | C13: 0.03
... A91: Q3-030 | B91: 5 | C91: 0.09
